{
  "manifestVersion": "3.2",
  "proxies": [
    {
      "address": "0x55D0db4Ca1A1986b4eDd92dd9f63952093954F3a",
      "txHash": "0x2c13642eb65637118b386a041f4dc5ee9f7de0733544b3be4e692d755a75b1d3",
      "kind": "transparent"
    },
    {
      "address": "0xAd0E90396e8bc7ae2C4F267a3aD27465863122F4",
      "txHash": "0x9b04a9023ed1bcebab17e85b4b42efc8fea5679e7ac77a56e56b4d48820e7207",
      "kind": "transparent"
    },
    {
      "address": "0x8e4481822B13F56448F246d31201Ea5845F7fb75",
      "txHash": "0xee292a6f6fa8034220b99feff511604dad72ce5e060b64876b2cdbf701b9948e",
      "kind": "transparent"
    },
    {
      "address": "0xC220Cfd72484dE4857508543A3A4f74AA119AA7c",
      "txHash": "0xcc2edaf5d72aa58f73e2f398ed9799cccb680fe4f073f4b96949ddd8392afe50",
      "kind": "transparent"
    },
    {
      "address": "0xc648f7B57d11CD00E9A7250bb7b912DE9aa24808",
      "txHash": "0x596a91a0d5a43d9f8c47bd79d98cc7d47c484b88f6b02090709f7a608656249e",
      "kind": "transparent"
    },
    {
      "address": "0x1BA0102B2aBa3863E7750133A90e63dfD6945D21",
      "txHash": "0x7c79fcc5840938515c7089ee40c03b8c275c4b991b66289a5746aeb29df57f90",
      "kind": "transparent"
    },
    {
      "address": "0xD2692a0e6Eef7F6ffFC227B2a70E6a07E08a2D5C",
      "txHash": "0x90b8daf76c759b382b5acdb212f9875c2bb82e953fbcdfd7a773668ab04a7e68",
      "kind": "transparent"
    },
    {
      "address": "0x7CB1Bc1eAe5Fcc19751c6739B8aeAFaCf26Da14F",
      "txHash": "0x4386f475fdf0d91c185334ef477260dcfe90004abe8e422d891de928fa8bb2d9",
      "kind": "transparent"
    }
  ],
  "impls": {
    "a2bdaa0e1e80344000c742cd36886eb6191c331f7bde4ec13ad73ab1e7663384": {
      "address": "0x2bB4002E385b6171e46Af2120340610686359dA6",
      "txHash": "0x8ffd841649c885baeb5b0a65f2652fbfc84e79ce59b953545b7ea5f9154041de",
      "layout": {
        "solcVersion": "0.8.16",
        "storage": [
          {
            "label": "_initialized",
            "offset": 0,
            "slot": "0",
            "type": "t_uint8",
            "contract": "Initializable",
            "src": "@openzeppelin/contracts-upgradeable/proxy/utils/Initializable.sol:63",
            "retypedFrom": "bool"
          },
          {
            "label": "_initializing",
            "offset": 1,
            "slot": "0",
            "type": "t_bool",
            "contract": "Initializable",
            "src": "@openzeppelin/contracts-upgradeable/proxy/utils/Initializable.sol:68"
          },
          {
            "label": "__gap",
            "offset": 0,
            "slot": "1",
            "type": "t_array(t_uint256)50_storage",
            "contract": "ContextUpgradeable",
            "src": "@openzeppelin/contracts-upgradeable/utils/ContextUpgradeable.sol:40"
          },
          {
            "label": "__gap",
            "offset": 0,
            "slot": "51",
            "type": "t_array(t_uint256)50_storage",
            "contract": "ERC165Upgradeable",
            "src": "@openzeppelin/contracts-upgradeable/utils/introspection/ERC165Upgradeable.sol:41"
          },
          {
            "label": "_roles",
            "offset": 0,
            "slot": "101",
            "type": "t_mapping(t_bytes32,t_struct(RoleData)169_storage)",
            "contract": "AccessControlUpgradeable",
            "src": "@openzeppelin/contracts-upgradeable/access/AccessControlUpgradeable.sol:57"
          },
          {
            "label": "__gap",
            "offset": 0,
            "slot": "102",
            "type": "t_array(t_uint256)49_storage",
            "contract": "AccessControlUpgradeable",
            "src": "@openzeppelin/contracts-upgradeable/access/AccessControlUpgradeable.sol:260"
          },
          {
            "label": "_roleMembers",
            "offset": 0,
            "slot": "151",
            "type": "t_mapping(t_bytes32,t_struct(AddressSet)9172_storage)",
            "contract": "AccessControlEnumerableUpgradeable",
            "src": "@openzeppelin/contracts-upgradeable/access/AccessControlEnumerableUpgradeable.sol:17"
          },
          {
            "label": "__gap",
            "offset": 0,
            "slot": "152",
            "type": "t_array(t_uint256)49_storage",
            "contract": "AccessControlEnumerableUpgradeable",
            "src": "@openzeppelin/contracts-upgradeable/access/AccessControlEnumerableUpgradeable.sol:76"
          },
          {
            "label": "contractManagerOfSkaleManager",
            "offset": 0,
            "slot": "201",
            "type": "t_contract(IContractManager)11020",
            "contract": "SkaleManagerClient",
            "src": "contracts/mainnet/SkaleManagerClient.sol:37"
          },
          {
            "label": "connectedChains",
            "offset": 0,
            "slot": "202",
            "type": "t_mapping(t_bytes32,t_struct(ConnectedChainInfo)12064_storage)",
            "contract": "MessageProxy",
            "src": "contracts/MessageProxy.sol:59"
          },
          {
            "label": "_deprecatedRegistryContracts",
            "offset": 0,
            "slot": "203",
            "type": "t_mapping(t_bytes32,t_mapping(t_address,t_bool))",
            "contract": "MessageProxy",
            "src": "contracts/MessageProxy.sol:61"
          },
          {
            "label": "gasLimit",
            "offset": 0,
            "slot": "204",
            "type": "t_uint256",
            "contract": "MessageProxy",
            "src": "contracts/MessageProxy.sol:63"
          },
          {
            "label": "communityPool",
            "offset": 0,
            "slot": "205",
            "type": "t_contract(ICommunityPool)10226",
            "contract": "MessageProxyForMainnet",
            "src": "contracts/mainnet/MessageProxyForMainnet.sol:72"
          },
          {
            "label": "headerMessageGasCost",
            "offset": 0,
            "slot": "206",
            "type": "t_uint256",
            "contract": "MessageProxyForMainnet",
            "src": "contracts/mainnet/MessageProxyForMainnet.sol:74"
          },
          {
            "label": "messageGasCost",
            "offset": 0,
            "slot": "207",
            "type": "t_uint256",
            "contract": "MessageProxyForMainnet",
            "src": "contracts/mainnet/MessageProxyForMainnet.sol:75"
          },
          {
            "label": "_registryContracts",
            "offset": 0,
            "slot": "208",
            "type": "t_mapping(t_bytes32,t_struct(AddressSet)9172_storage)",
            "contract": "MessageProxyForMainnet",
            "src": "contracts/mainnet/MessageProxyForMainnet.sol:80"
          },
          {
            "label": "version",
            "offset": 0,
            "slot": "209",
            "type": "t_string_storage",
            "contract": "MessageProxyForMainnet",
            "src": "contracts/mainnet/MessageProxyForMainnet.sol:81"
          },
          {
            "label": "messageInProgress",
            "offset": 0,
            "slot": "210",
            "type": "t_bool",
            "contract": "MessageProxyForMainnet",
            "src": "contracts/mainnet/MessageProxyForMainnet.sol:82"
          },
          {
            "label": "pauseInfo",
            "offset": 0,
            "slot": "211",
            "type": "t_mapping(t_bytes32,t_struct(Pause)20546_storage)",
            "contract": "MessageProxyForMainnet",
            "src": "contracts/mainnet/MessageProxyForMainnet.sol:85"
          },
          {
            "label": "_reimbursedContracts",
            "offset": 0,
            "slot": "212",
            "type": "t_mapping(t_bytes32,t_struct(AddressSet)9172_storage)",
            "contract": "MessageProxyForMainnet",
            "src": "contracts/mainnet/MessageProxyForMainnet.sol:88"
          }
        ],
        "types": {
          "t_address": {
            "label": "address",
            "numberOfBytes": "20"
          },
          "t_array(t_bytes32)dyn_storage": {
            "label": "bytes32[]",
            "numberOfBytes": "32"
          },
          "t_array(t_uint256)49_storage": {
            "label": "uint256[49]",
            "numberOfBytes": "1568"
          },
          "t_array(t_uint256)50_storage": {
            "label": "uint256[50]",
            "numberOfBytes": "1600"
          },
          "t_bool": {
            "label": "bool",
            "numberOfBytes": "1"
          },
          "t_bytes32": {
            "label": "bytes32",
            "numberOfBytes": "32"
          },
          "t_contract(ICommunityPool)10226": {
            "label": "contract ICommunityPool",
            "numberOfBytes": "20"
          },
          "t_contract(IContractManager)11020": {
            "label": "contract IContractManager",
            "numberOfBytes": "20"
          },
          "t_mapping(t_address,t_bool)": {
            "label": "mapping(address => bool)",
            "numberOfBytes": "32"
          },
          "t_mapping(t_bytes32,t_mapping(t_address,t_bool))": {
            "label": "mapping(bytes32 => mapping(address => bool))",
            "numberOfBytes": "32"
          },
          "t_mapping(t_bytes32,t_struct(AddressSet)9172_storage)": {
            "label": "mapping(bytes32 => struct EnumerableSetUpgradeable.AddressSet)",
            "numberOfBytes": "32"
          },
          "t_mapping(t_bytes32,t_struct(ConnectedChainInfo)12064_storage)": {
            "label": "mapping(bytes32 => struct MessageProxy.ConnectedChainInfo)",
            "numberOfBytes": "32"
          },
          "t_mapping(t_bytes32,t_struct(Pause)20546_storage)": {
            "label": "mapping(bytes32 => struct MessageProxyForMainnet.Pause)",
            "numberOfBytes": "32"
          },
          "t_mapping(t_bytes32,t_struct(RoleData)169_storage)": {
            "label": "mapping(bytes32 => struct AccessControlUpgradeable.RoleData)",
            "numberOfBytes": "32"
          },
          "t_mapping(t_bytes32,t_uint256)": {
            "label": "mapping(bytes32 => uint256)",
            "numberOfBytes": "32"
          },
          "t_string_storage": {
            "label": "string",
            "numberOfBytes": "32"
          },
          "t_struct(AddressSet)9172_storage": {
            "label": "struct EnumerableSetUpgradeable.AddressSet",
            "members": [
              {
                "label": "_inner",
                "type": "t_struct(Set)8857_storage",
                "offset": 0,
                "slot": "0"
              }
            ],
            "numberOfBytes": "64"
          },
          "t_struct(ConnectedChainInfo)12064_storage": {
            "label": "struct MessageProxy.ConnectedChainInfo",
            "members": [
              {
                "label": "incomingMessageCounter",
                "type": "t_uint256",
                "offset": 0,
                "slot": "0"
              },
              {
                "label": "outgoingMessageCounter",
                "type": "t_uint256",
                "offset": 0,
                "slot": "1"
              },
              {
                "label": "inited",
                "type": "t_bool",
                "offset": 0,
                "slot": "2"
              },
              {
                "label": "lastOutgoingMessageBlockId",
                "type": "t_uint256",
                "offset": 0,
                "slot": "3"
              }
            ],
            "numberOfBytes": "128"
          },
          "t_struct(Pause)20546_storage": {
            "label": "struct MessageProxyForMainnet.Pause",
            "members": [
              {
                "label": "paused",
                "type": "t_bool",
                "offset": 0,
                "slot": "0"
              }
            ],
            "numberOfBytes": "32"
          },
          "t_struct(RoleData)169_storage": {
            "label": "struct AccessControlUpgradeable.RoleData",
            "members": [
              {
                "label": "members",
                "type": "t_mapping(t_address,t_bool)",
                "offset": 0,
                "slot": "0"
              },
              {
                "label": "adminRole",
                "type": "t_bytes32",
                "offset": 0,
                "slot": "1"
              }
            ],
            "numberOfBytes": "64"
          },
          "t_struct(Set)8857_storage": {
            "label": "struct EnumerableSetUpgradeable.Set",
            "members": [
              {
                "label": "_values",
                "type": "t_array(t_bytes32)dyn_storage",
                "offset": 0,
                "slot": "0"
              },
              {
                "label": "_indexes",
                "type": "t_mapping(t_bytes32,t_uint256)",
                "offset": 0,
                "slot": "1"
              }
            ],
            "numberOfBytes": "64"
          },
          "t_uint256": {
            "label": "uint256",
            "numberOfBytes": "32"
          },
          "t_uint8": {
            "label": "uint8",
            "numberOfBytes": "1"
          }
        },
        "namespaces": {}
      }
    },
    "66980706ada9cff2a0530d442072a98ac056b55a7503146bffbda741433d376d": {
      "address": "0x6cDb63C8Fd47C97240f806b6Ec144781d568e952",
      "txHash": "0x2518613043407e8509bd3177d4ce1f7c7d5e308f25acc33b17397adfc61923a1",
      "layout": {
        "solcVersion": "0.8.16",
        "storage": [
          {
            "label": "_initialized",
            "offset": 0,
            "slot": "0",
            "type": "t_uint8",
            "contract": "Initializable",
            "src": "@openzeppelin/contracts-upgradeable/proxy/utils/Initializable.sol:63",
            "retypedFrom": "bool"
          },
          {
            "label": "_initializing",
            "offset": 1,
            "slot": "0",
            "type": "t_bool",
            "contract": "Initializable",
            "src": "@openzeppelin/contracts-upgradeable/proxy/utils/Initializable.sol:68"
          },
          {
            "label": "__gap",
            "offset": 0,
            "slot": "1",
            "type": "t_array(t_uint256)50_storage",
            "contract": "ContextUpgradeable",
            "src": "@openzeppelin/contracts-upgradeable/utils/ContextUpgradeable.sol:40"
          },
          {
            "label": "__gap",
            "offset": 0,
            "slot": "51",
            "type": "t_array(t_uint256)50_storage",
            "contract": "ERC165Upgradeable",
            "src": "@openzeppelin/contracts-upgradeable/utils/introspection/ERC165Upgradeable.sol:41"
          },
          {
            "label": "_roles",
            "offset": 0,
            "slot": "101",
            "type": "t_mapping(t_bytes32,t_struct(RoleData)169_storage)",
            "contract": "AccessControlUpgradeable",
            "src": "@openzeppelin/contracts-upgradeable/access/AccessControlUpgradeable.sol:57"
          },
          {
            "label": "__gap",
            "offset": 0,
            "slot": "102",
            "type": "t_array(t_uint256)49_storage",
            "contract": "AccessControlUpgradeable",
            "src": "@openzeppelin/contracts-upgradeable/access/AccessControlUpgradeable.sol:260"
          },
          {
            "label": "_roleMembers",
            "offset": 0,
            "slot": "151",
            "type": "t_mapping(t_bytes32,t_struct(AddressSet)9172_storage)",
            "contract": "AccessControlEnumerableUpgradeable",
            "src": "@openzeppelin/contracts-upgradeable/access/AccessControlEnumerableUpgradeable.sol:17"
          },
          {
            "label": "__gap",
            "offset": 0,
            "slot": "152",
            "type": "t_array(t_uint256)49_storage",
            "contract": "AccessControlEnumerableUpgradeable",
            "src": "@openzeppelin/contracts-upgradeable/access/AccessControlEnumerableUpgradeable.sol:76"
          },
          {
            "label": "contractManagerOfSkaleManager",
            "offset": 0,
            "slot": "201",
            "type": "t_contract(IContractManager)11020",
            "contract": "SkaleManagerClient",
            "src": "contracts/mainnet/SkaleManagerClient.sol:37"
          },
          {
            "label": "messageProxy",
            "offset": 0,
            "slot": "202",
            "type": "t_contract(IMessageProxyForMainnet)10412",
            "contract": "Twin",
            "src": "contracts/mainnet/Twin.sol:38"
          },
          {
            "label": "schainLinks",
            "offset": 0,
            "slot": "203",
            "type": "t_mapping(t_bytes32,t_address)",
            "contract": "Twin",
            "src": "contracts/mainnet/Twin.sol:39"
          },
          {
            "label": "_mainnetContracts",
            "offset": 0,
            "slot": "204",
            "type": "t_struct(AddressSet)9172_storage",
            "contract": "Linker",
            "src": "contracts/mainnet/Linker.sol:44"
          },
          {
            "label": "_interchainConnections",
            "offset": 0,
            "slot": "206",
            "type": "t_mapping(t_bytes32,t_bool)",
            "contract": "Linker",
            "src": "contracts/mainnet/Linker.sol:47"
          },
          {
            "label": "statuses",
            "offset": 0,
            "slot": "207",
            "type": "t_mapping(t_bytes32,t_enum(KillProcess)20131)",
            "contract": "Linker",
            "src": "contracts/mainnet/Linker.sol:51"
          }
        ],
        "types": {
          "t_address": {
            "label": "address",
            "numberOfBytes": "20"
          },
          "t_array(t_bytes32)dyn_storage": {
            "label": "bytes32[]",
            "numberOfBytes": "32"
          },
          "t_array(t_uint256)49_storage": {
            "label": "uint256[49]",
            "numberOfBytes": "1568"
          },
          "t_array(t_uint256)50_storage": {
            "label": "uint256[50]",
            "numberOfBytes": "1600"
          },
          "t_bool": {
            "label": "bool",
            "numberOfBytes": "1"
          },
          "t_bytes32": {
            "label": "bytes32",
            "numberOfBytes": "32"
          },
          "t_contract(IContractManager)11020": {
            "label": "contract IContractManager",
            "numberOfBytes": "20"
          },
          "t_contract(IMessageProxyForMainnet)10412": {
            "label": "contract IMessageProxyForMainnet",
            "numberOfBytes": "20"
          },
          "t_enum(KillProcess)20131": {
            "label": "enum Linker.KillProcess",
            "members": [
              "NotKilled",
              "PartiallyKilledBySchainOwner",
              "PartiallyKilledByContractOwner",
              "Killed"
            ],
            "numberOfBytes": "1"
          },
          "t_mapping(t_address,t_bool)": {
            "label": "mapping(address => bool)",
            "numberOfBytes": "32"
          },
          "t_mapping(t_bytes32,t_address)": {
            "label": "mapping(bytes32 => address)",
            "numberOfBytes": "32"
          },
          "t_mapping(t_bytes32,t_bool)": {
            "label": "mapping(bytes32 => bool)",
            "numberOfBytes": "32"
          },
          "t_mapping(t_bytes32,t_enum(KillProcess)20131)": {
            "label": "mapping(bytes32 => enum Linker.KillProcess)",
            "numberOfBytes": "32"
          },
          "t_mapping(t_bytes32,t_struct(AddressSet)9172_storage)": {
            "label": "mapping(bytes32 => struct EnumerableSetUpgradeable.AddressSet)",
            "numberOfBytes": "32"
          },
          "t_mapping(t_bytes32,t_struct(RoleData)169_storage)": {
            "label": "mapping(bytes32 => struct AccessControlUpgradeable.RoleData)",
            "numberOfBytes": "32"
          },
          "t_mapping(t_bytes32,t_uint256)": {
            "label": "mapping(bytes32 => uint256)",
            "numberOfBytes": "32"
          },
          "t_struct(AddressSet)9172_storage": {
            "label": "struct EnumerableSetUpgradeable.AddressSet",
            "members": [
              {
                "label": "_inner",
                "type": "t_struct(Set)8857_storage",
                "offset": 0,
                "slot": "0"
              }
            ],
            "numberOfBytes": "64"
          },
          "t_struct(RoleData)169_storage": {
            "label": "struct AccessControlUpgradeable.RoleData",
            "members": [
              {
                "label": "members",
                "type": "t_mapping(t_address,t_bool)",
                "offset": 0,
                "slot": "0"
              },
              {
                "label": "adminRole",
                "type": "t_bytes32",
                "offset": 0,
                "slot": "1"
              }
            ],
            "numberOfBytes": "64"
          },
          "t_struct(Set)8857_storage": {
            "label": "struct EnumerableSetUpgradeable.Set",
            "members": [
              {
                "label": "_values",
                "type": "t_array(t_bytes32)dyn_storage",
                "offset": 0,
                "slot": "0"
              },
              {
                "label": "_indexes",
                "type": "t_mapping(t_bytes32,t_uint256)",
                "offset": 0,
                "slot": "1"
              }
            ],
            "numberOfBytes": "64"
          },
          "t_uint256": {
            "label": "uint256",
            "numberOfBytes": "32"
          },
          "t_uint8": {
            "label": "uint8",
            "numberOfBytes": "1"
          }
        },
        "namespaces": {}
      }
    },
    "6a717c057e9bdaa2975701da4fd44b6532df72918813a2eb93a7bddb466b0e4e": {
      "address": "0x2b60823B24c5391A7373F25eD16DDfCfA552e87A",
      "txHash": "0x5286bce8bbc61bee853d22c287536bd8a638b3509de6faa40c4e1c05194fc708",
      "layout": {
        "solcVersion": "0.8.16",
        "storage": [
          {
            "label": "_initialized",
            "offset": 0,
            "slot": "0",
            "type": "t_uint8",
            "contract": "Initializable",
            "src": "@openzeppelin/contracts-upgradeable/proxy/utils/Initializable.sol:63",
            "retypedFrom": "bool"
          },
          {
            "label": "_initializing",
            "offset": 1,
            "slot": "0",
            "type": "t_bool",
            "contract": "Initializable",
            "src": "@openzeppelin/contracts-upgradeable/proxy/utils/Initializable.sol:68"
          },
          {
            "label": "__gap",
            "offset": 0,
            "slot": "1",
            "type": "t_array(t_uint256)50_storage",
            "contract": "ContextUpgradeable",
            "src": "@openzeppelin/contracts-upgradeable/utils/ContextUpgradeable.sol:40"
          },
          {
            "label": "__gap",
            "offset": 0,
            "slot": "51",
            "type": "t_array(t_uint256)50_storage",
            "contract": "ERC165Upgradeable",
            "src": "@openzeppelin/contracts-upgradeable/utils/introspection/ERC165Upgradeable.sol:41"
          },
          {
            "label": "_roles",
            "offset": 0,
            "slot": "101",
            "type": "t_mapping(t_bytes32,t_struct(RoleData)169_storage)",
            "contract": "AccessControlUpgradeable",
            "src": "@openzeppelin/contracts-upgradeable/access/AccessControlUpgradeable.sol:57"
          },
          {
            "label": "__gap",
            "offset": 0,
            "slot": "102",
            "type": "t_array(t_uint256)49_storage",
            "contract": "AccessControlUpgradeable",
            "src": "@openzeppelin/contracts-upgradeable/access/AccessControlUpgradeable.sol:260"
          },
          {
            "label": "_roleMembers",
            "offset": 0,
            "slot": "151",
            "type": "t_mapping(t_bytes32,t_struct(AddressSet)9172_storage)",
            "contract": "AccessControlEnumerableUpgradeable",
            "src": "@openzeppelin/contracts-upgradeable/access/AccessControlEnumerableUpgradeable.sol:17"
          },
          {
            "label": "__gap",
            "offset": 0,
            "slot": "152",
            "type": "t_array(t_uint256)49_storage",
            "contract": "AccessControlEnumerableUpgradeable",
            "src": "@openzeppelin/contracts-upgradeable/access/AccessControlEnumerableUpgradeable.sol:76"
          },
          {
            "label": "contractManagerOfSkaleManager",
            "offset": 0,
            "slot": "201",
            "type": "t_contract(IContractManager)11020",
            "contract": "SkaleManagerClient",
            "src": "contracts/mainnet/SkaleManagerClient.sol:37"
          },
          {
            "label": "messageProxy",
            "offset": 0,
            "slot": "202",
            "type": "t_contract(IMessageProxyForMainnet)10412",
            "contract": "Twin",
            "src": "contracts/mainnet/Twin.sol:38"
          },
          {
            "label": "schainLinks",
            "offset": 0,
            "slot": "203",
            "type": "t_mapping(t_bytes32,t_address)",
            "contract": "Twin",
            "src": "contracts/mainnet/Twin.sol:39"
          },
          {
            "label": "_userWallets",
            "offset": 0,
            "slot": "204",
            "type": "t_mapping(t_address,t_mapping(t_bytes32,t_uint256))",
            "contract": "CommunityPool",
            "src": "contracts/mainnet/CommunityPool.sol:44"
          },
          {
            "label": "activeUsers",
            "offset": 0,
            "slot": "205",
            "type": "t_mapping(t_address,t_mapping(t_bytes32,t_bool))",
            "contract": "CommunityPool",
            "src": "contracts/mainnet/CommunityPool.sol:47"
          },
          {
            "label": "minTransactionGas",
            "offset": 0,
            "slot": "206",
            "type": "t_uint256",
            "contract": "CommunityPool",
            "src": "contracts/mainnet/CommunityPool.sol:49"
          },
          {
            "label": "multiplierNumerator",
            "offset": 0,
            "slot": "207",
            "type": "t_uint256",
            "contract": "CommunityPool",
            "src": "contracts/mainnet/CommunityPool.sol:51"
          },
          {
            "label": "multiplierDivider",
            "offset": 0,
            "slot": "208",
            "type": "t_uint256",
            "contract": "CommunityPool",
            "src": "contracts/mainnet/CommunityPool.sol:52"
          }
        ],
        "types": {
          "t_address": {
            "label": "address",
            "numberOfBytes": "20"
          },
          "t_array(t_bytes32)dyn_storage": {
            "label": "bytes32[]",
            "numberOfBytes": "32"
          },
          "t_array(t_uint256)49_storage": {
            "label": "uint256[49]",
            "numberOfBytes": "1568"
          },
          "t_array(t_uint256)50_storage": {
            "label": "uint256[50]",
            "numberOfBytes": "1600"
          },
          "t_bool": {
            "label": "bool",
            "numberOfBytes": "1"
          },
          "t_bytes32": {
            "label": "bytes32",
            "numberOfBytes": "32"
          },
          "t_contract(IContractManager)11020": {
            "label": "contract IContractManager",
            "numberOfBytes": "20"
          },
          "t_contract(IMessageProxyForMainnet)10412": {
            "label": "contract IMessageProxyForMainnet",
            "numberOfBytes": "20"
          },
          "t_mapping(t_address,t_bool)": {
            "label": "mapping(address => bool)",
            "numberOfBytes": "32"
          },
          "t_mapping(t_address,t_mapping(t_bytes32,t_bool))": {
            "label": "mapping(address => mapping(bytes32 => bool))",
            "numberOfBytes": "32"
          },
          "t_mapping(t_address,t_mapping(t_bytes32,t_uint256))": {
            "label": "mapping(address => mapping(bytes32 => uint256))",
            "numberOfBytes": "32"
          },
          "t_mapping(t_bytes32,t_address)": {
            "label": "mapping(bytes32 => address)",
            "numberOfBytes": "32"
          },
          "t_mapping(t_bytes32,t_bool)": {
            "label": "mapping(bytes32 => bool)",
            "numberOfBytes": "32"
          },
          "t_mapping(t_bytes32,t_struct(AddressSet)9172_storage)": {
            "label": "mapping(bytes32 => struct EnumerableSetUpgradeable.AddressSet)",
            "numberOfBytes": "32"
          },
          "t_mapping(t_bytes32,t_struct(RoleData)169_storage)": {
            "label": "mapping(bytes32 => struct AccessControlUpgradeable.RoleData)",
            "numberOfBytes": "32"
          },
          "t_mapping(t_bytes32,t_uint256)": {
            "label": "mapping(bytes32 => uint256)",
            "numberOfBytes": "32"
          },
          "t_struct(AddressSet)9172_storage": {
            "label": "struct EnumerableSetUpgradeable.AddressSet",
            "members": [
              {
                "label": "_inner",
                "type": "t_struct(Set)8857_storage",
                "offset": 0,
                "slot": "0"
              }
            ],
            "numberOfBytes": "64"
          },
          "t_struct(RoleData)169_storage": {
            "label": "struct AccessControlUpgradeable.RoleData",
            "members": [
              {
                "label": "members",
                "type": "t_mapping(t_address,t_bool)",
                "offset": 0,
                "slot": "0"
              },
              {
                "label": "adminRole",
                "type": "t_bytes32",
                "offset": 0,
                "slot": "1"
              }
            ],
            "numberOfBytes": "64"
          },
          "t_struct(Set)8857_storage": {
            "label": "struct EnumerableSetUpgradeable.Set",
            "members": [
              {
                "label": "_values",
                "type": "t_array(t_bytes32)dyn_storage",
                "offset": 0,
                "slot": "0"
              },
              {
                "label": "_indexes",
                "type": "t_mapping(t_bytes32,t_uint256)",
                "offset": 0,
                "slot": "1"
              }
            ],
            "numberOfBytes": "64"
          },
          "t_uint256": {
            "label": "uint256",
            "numberOfBytes": "32"
          },
          "t_uint8": {
            "label": "uint8",
            "numberOfBytes": "1"
          }
        },
        "namespaces": {}
      }
    },
    "9769356c8b8f1bee2543f6abcaebae75d76d1c8e646cb8552ce60c5783543fc1": {
      "address": "0x4D45005E55982E5D46e057f7D1D35E7A39F11D37",
      "txHash": "0x29797e6c0da7b0c09b24a23bdfd469a538fc87f15768900af3775a045cae8d5d",
      "layout": {
        "solcVersion": "0.8.16",
        "storage": [
          {
            "label": "_initialized",
            "offset": 0,
            "slot": "0",
            "type": "t_uint8",
            "contract": "Initializable",
            "src": "@openzeppelin/contracts-upgradeable/proxy/utils/Initializable.sol:63",
            "retypedFrom": "bool"
          },
          {
            "label": "_initializing",
            "offset": 1,
            "slot": "0",
            "type": "t_bool",
            "contract": "Initializable",
            "src": "@openzeppelin/contracts-upgradeable/proxy/utils/Initializable.sol:68"
          },
          {
            "label": "__gap",
            "offset": 0,
            "slot": "1",
            "type": "t_array(t_uint256)50_storage",
            "contract": "ContextUpgradeable",
            "src": "@openzeppelin/contracts-upgradeable/utils/ContextUpgradeable.sol:40"
          },
          {
            "label": "__gap",
            "offset": 0,
            "slot": "51",
            "type": "t_array(t_uint256)50_storage",
            "contract": "ERC165Upgradeable",
            "src": "@openzeppelin/contracts-upgradeable/utils/introspection/ERC165Upgradeable.sol:41"
          },
          {
            "label": "_roles",
            "offset": 0,
            "slot": "101",
            "type": "t_mapping(t_bytes32,t_struct(RoleData)169_storage)",
            "contract": "AccessControlUpgradeable",
            "src": "@openzeppelin/contracts-upgradeable/access/AccessControlUpgradeable.sol:57"
          },
          {
            "label": "__gap",
            "offset": 0,
            "slot": "102",
            "type": "t_array(t_uint256)49_storage",
            "contract": "AccessControlUpgradeable",
            "src": "@openzeppelin/contracts-upgradeable/access/AccessControlUpgradeable.sol:260"
          },
          {
            "label": "_roleMembers",
            "offset": 0,
            "slot": "151",
            "type": "t_mapping(t_bytes32,t_struct(AddressSet)9172_storage)",
            "contract": "AccessControlEnumerableUpgradeable",
            "src": "@openzeppelin/contracts-upgradeable/access/AccessControlEnumerableUpgradeable.sol:17"
          },
          {
            "label": "__gap",
            "offset": 0,
            "slot": "152",
            "type": "t_array(t_uint256)49_storage",
            "contract": "AccessControlEnumerableUpgradeable",
            "src": "@openzeppelin/contracts-upgradeable/access/AccessControlEnumerableUpgradeable.sol:76"
          },
          {
            "label": "contractManagerOfSkaleManager",
            "offset": 0,
            "slot": "201",
            "type": "t_contract(IContractManager)11020",
            "contract": "SkaleManagerClient",
            "src": "contracts/mainnet/SkaleManagerClient.sol:37"
          },
          {
            "label": "messageProxy",
            "offset": 0,
            "slot": "202",
            "type": "t_contract(IMessageProxyForMainnet)10412",
            "contract": "Twin",
            "src": "contracts/mainnet/Twin.sol:38"
          },
          {
            "label": "schainLinks",
            "offset": 0,
            "slot": "203",
            "type": "t_mapping(t_bytes32,t_address)",
            "contract": "Twin",
            "src": "contracts/mainnet/Twin.sol:39"
          },
          {
            "label": "linker",
            "offset": 0,
            "slot": "204",
            "type": "t_contract(ILinker)10325",
            "contract": "DepositBox",
            "src": "contracts/mainnet/DepositBox.sol:36"
          },
          {
            "label": "_automaticDeploy",
            "offset": 0,
            "slot": "205",
            "type": "t_mapping(t_bytes32,t_bool)",
            "contract": "DepositBox",
            "src": "contracts/mainnet/DepositBox.sol:39"
          },
          {
            "label": "approveTransfers",
            "offset": 0,
            "slot": "206",
            "type": "t_mapping(t_address,t_uint256)",
            "contract": "DepositBoxEth",
            "src": "contracts/mainnet/DepositBoxes/DepositBoxEth.sol:39"
          },
          {
            "label": "transferredAmount",
            "offset": 0,
            "slot": "207",
            "type": "t_mapping(t_bytes32,t_uint256)",
            "contract": "DepositBoxEth",
            "src": "contracts/mainnet/DepositBoxes/DepositBoxEth.sol:41"
          },
          {
            "label": "activeEthTransfers",
            "offset": 0,
            "slot": "208",
            "type": "t_mapping(t_bytes32,t_bool)",
            "contract": "DepositBoxEth",
            "src": "contracts/mainnet/DepositBoxes/DepositBoxEth.sol:43"
          }
        ],
        "types": {
          "t_address": {
            "label": "address",
            "numberOfBytes": "20"
          },
          "t_array(t_bytes32)dyn_storage": {
            "label": "bytes32[]",
            "numberOfBytes": "32"
          },
          "t_array(t_uint256)49_storage": {
            "label": "uint256[49]",
            "numberOfBytes": "1568"
          },
          "t_array(t_uint256)50_storage": {
            "label": "uint256[50]",
            "numberOfBytes": "1600"
          },
          "t_bool": {
            "label": "bool",
            "numberOfBytes": "1"
          },
          "t_bytes32": {
            "label": "bytes32",
            "numberOfBytes": "32"
          },
          "t_contract(IContractManager)11020": {
            "label": "contract IContractManager",
            "numberOfBytes": "20"
          },
          "t_contract(ILinker)10325": {
            "label": "contract ILinker",
            "numberOfBytes": "20"
          },
          "t_contract(IMessageProxyForMainnet)10412": {
            "label": "contract IMessageProxyForMainnet",
            "numberOfBytes": "20"
          },
          "t_mapping(t_address,t_bool)": {
            "label": "mapping(address => bool)",
            "numberOfBytes": "32"
          },
          "t_mapping(t_address,t_uint256)": {
            "label": "mapping(address => uint256)",
            "numberOfBytes": "32"
          },
          "t_mapping(t_bytes32,t_address)": {
            "label": "mapping(bytes32 => address)",
            "numberOfBytes": "32"
          },
          "t_mapping(t_bytes32,t_bool)": {
            "label": "mapping(bytes32 => bool)",
            "numberOfBytes": "32"
          },
          "t_mapping(t_bytes32,t_struct(AddressSet)9172_storage)": {
            "label": "mapping(bytes32 => struct EnumerableSetUpgradeable.AddressSet)",
            "numberOfBytes": "32"
          },
          "t_mapping(t_bytes32,t_struct(RoleData)169_storage)": {
            "label": "mapping(bytes32 => struct AccessControlUpgradeable.RoleData)",
            "numberOfBytes": "32"
          },
          "t_mapping(t_bytes32,t_uint256)": {
            "label": "mapping(bytes32 => uint256)",
            "numberOfBytes": "32"
          },
          "t_struct(AddressSet)9172_storage": {
            "label": "struct EnumerableSetUpgradeable.AddressSet",
            "members": [
              {
                "label": "_inner",
                "type": "t_struct(Set)8857_storage",
                "offset": 0,
                "slot": "0"
              }
            ],
            "numberOfBytes": "64"
          },
          "t_struct(RoleData)169_storage": {
            "label": "struct AccessControlUpgradeable.RoleData",
            "members": [
              {
                "label": "members",
                "type": "t_mapping(t_address,t_bool)",
                "offset": 0,
                "slot": "0"
              },
              {
                "label": "adminRole",
                "type": "t_bytes32",
                "offset": 0,
                "slot": "1"
              }
            ],
            "numberOfBytes": "64"
          },
          "t_struct(Set)8857_storage": {
            "label": "struct EnumerableSetUpgradeable.Set",
            "members": [
              {
                "label": "_values",
                "type": "t_array(t_bytes32)dyn_storage",
                "offset": 0,
                "slot": "0"
              },
              {
                "label": "_indexes",
                "type": "t_mapping(t_bytes32,t_uint256)",
                "offset": 0,
                "slot": "1"
              }
            ],
            "numberOfBytes": "64"
          },
          "t_uint256": {
            "label": "uint256",
            "numberOfBytes": "32"
          },
          "t_uint8": {
            "label": "uint8",
            "numberOfBytes": "1"
          }
        },
        "namespaces": {}
      }
    },
    "7e8da67c29fe172c3548236ee9e1e7ff7f7f6fc3bf9ef59aedae5052acd94326": {
      "address": "0xDc053433368185A8e2CF4584403456F34321A1bA",
      "txHash": "0xa5d87c69ab49eae130a0c0b639ebc17b3c6c86371e90219b1f2e8f205d239304",
      "layout": {
        "solcVersion": "0.8.16",
        "storage": [
          {
            "label": "_initialized",
            "offset": 0,
            "slot": "0",
            "type": "t_uint8",
            "contract": "Initializable",
            "src": "@openzeppelin/contracts-upgradeable/proxy/utils/Initializable.sol:63",
            "retypedFrom": "bool"
          },
          {
            "label": "_initializing",
            "offset": 1,
            "slot": "0",
            "type": "t_bool",
            "contract": "Initializable",
            "src": "@openzeppelin/contracts-upgradeable/proxy/utils/Initializable.sol:68"
          },
          {
            "label": "__gap",
            "offset": 0,
            "slot": "1",
            "type": "t_array(t_uint256)50_storage",
            "contract": "ContextUpgradeable",
            "src": "@openzeppelin/contracts-upgradeable/utils/ContextUpgradeable.sol:40"
          },
          {
            "label": "__gap",
            "offset": 0,
            "slot": "51",
            "type": "t_array(t_uint256)50_storage",
            "contract": "ERC165Upgradeable",
            "src": "@openzeppelin/contracts-upgradeable/utils/introspection/ERC165Upgradeable.sol:41"
          },
          {
            "label": "_roles",
            "offset": 0,
            "slot": "101",
            "type": "t_mapping(t_bytes32,t_struct(RoleData)169_storage)",
            "contract": "AccessControlUpgradeable",
            "src": "@openzeppelin/contracts-upgradeable/access/AccessControlUpgradeable.sol:57"
          },
          {
            "label": "__gap",
            "offset": 0,
            "slot": "102",
            "type": "t_array(t_uint256)49_storage",
            "contract": "AccessControlUpgradeable",
            "src": "@openzeppelin/contracts-upgradeable/access/AccessControlUpgradeable.sol:260"
          },
          {
            "label": "_roleMembers",
            "offset": 0,
            "slot": "151",
            "type": "t_mapping(t_bytes32,t_struct(AddressSet)9172_storage)",
            "contract": "AccessControlEnumerableUpgradeable",
            "src": "@openzeppelin/contracts-upgradeable/access/AccessControlEnumerableUpgradeable.sol:17"
          },
          {
            "label": "__gap",
            "offset": 0,
            "slot": "152",
            "type": "t_array(t_uint256)49_storage",
            "contract": "AccessControlEnumerableUpgradeable",
            "src": "@openzeppelin/contracts-upgradeable/access/AccessControlEnumerableUpgradeable.sol:76"
          },
          {
            "label": "contractManagerOfSkaleManager",
            "offset": 0,
            "slot": "201",
            "type": "t_contract(IContractManager)11020",
            "contract": "SkaleManagerClient",
            "src": "contracts/mainnet/SkaleManagerClient.sol:37"
          },
          {
            "label": "messageProxy",
            "offset": 0,
            "slot": "202",
            "type": "t_contract(IMessageProxyForMainnet)10412",
            "contract": "Twin",
            "src": "contracts/mainnet/Twin.sol:38"
          },
          {
            "label": "schainLinks",
            "offset": 0,
            "slot": "203",
            "type": "t_mapping(t_bytes32,t_address)",
            "contract": "Twin",
            "src": "contracts/mainnet/Twin.sol:39"
          },
          {
            "label": "linker",
            "offset": 0,
            "slot": "204",
            "type": "t_contract(ILinker)10325",
            "contract": "DepositBox",
            "src": "contracts/mainnet/DepositBox.sol:36"
          },
          {
            "label": "_automaticDeploy",
            "offset": 0,
            "slot": "205",
            "type": "t_mapping(t_bytes32,t_bool)",
            "contract": "DepositBox",
            "src": "contracts/mainnet/DepositBox.sol:39"
          },
          {
            "label": "_deprecatedSchainToERC20",
            "offset": 0,
            "slot": "206",
            "type": "t_mapping(t_bytes32,t_mapping(t_address,t_bool))",
            "contract": "DepositBoxERC20",
            "src": "contracts/mainnet/DepositBoxes/DepositBoxERC20.sol:84"
          },
          {
            "label": "transferredAmount",
            "offset": 0,
            "slot": "207",
            "type": "t_mapping(t_bytes32,t_mapping(t_address,t_uint256))",
            "contract": "DepositBoxERC20",
            "src": "contracts/mainnet/DepositBoxes/DepositBoxERC20.sol:85"
          },
          {
            "label": "_schainToERC20",
            "offset": 0,
            "slot": "208",
            "type": "t_mapping(t_bytes32,t_struct(AddressSet)9172_storage)",
            "contract": "DepositBoxERC20",
            "src": "contracts/mainnet/DepositBoxes/DepositBoxERC20.sol:86"
          },
          {
            "label": "_delayConfig",
            "offset": 0,
            "slot": "209",
            "type": "t_mapping(t_bytes32,t_struct(DelayConfig)16887_storage)",
            "contract": "DepositBoxERC20",
            "src": "contracts/mainnet/DepositBoxes/DepositBoxERC20.sol:90"
          },
          {
            "label": "delayedTransfersSize",
            "offset": 0,
            "slot": "210",
            "type": "t_uint256",
            "contract": "DepositBoxERC20",
            "src": "contracts/mainnet/DepositBoxes/DepositBoxERC20.sol:92"
          },
          {
            "label": "delayedTransfers",
            "offset": 0,
            "slot": "211",
            "type": "t_mapping(t_uint256,t_struct(DelayedTransfer)16875_storage)",
            "contract": "DepositBoxERC20",
            "src": "contracts/mainnet/DepositBoxes/DepositBoxERC20.sol:94"
          },
          {
            "label": "delayedTransfersByReceiver",
            "offset": 0,
            "slot": "212",
            "type": "t_mapping(t_address,t_struct(Bytes32Deque)8524_storage)",
            "contract": "DepositBoxERC20",
            "src": "contracts/mainnet/DepositBoxes/DepositBoxERC20.sol:96"
          }
        ],
        "types": {
          "t_address": {
            "label": "address",
            "numberOfBytes": "20"
          },
          "t_array(t_bytes32)dyn_storage": {
            "label": "bytes32[]",
            "numberOfBytes": "32"
          },
          "t_array(t_uint256)49_storage": {
            "label": "uint256[49]",
            "numberOfBytes": "1568"
          },
          "t_array(t_uint256)50_storage": {
            "label": "uint256[50]",
            "numberOfBytes": "1600"
          },
          "t_bool": {
            "label": "bool",
            "numberOfBytes": "1"
          },
          "t_bytes32": {
            "label": "bytes32",
            "numberOfBytes": "32"
          },
          "t_contract(IContractManager)11020": {
            "label": "contract IContractManager",
            "numberOfBytes": "20"
          },
          "t_contract(ILinker)10325": {
            "label": "contract ILinker",
            "numberOfBytes": "20"
          },
          "t_contract(IMessageProxyForMainnet)10412": {
            "label": "contract IMessageProxyForMainnet",
            "numberOfBytes": "20"
          },
          "t_enum(DelayedTransferStatus)16861": {
            "label": "enum DepositBoxERC20.DelayedTransferStatus",
            "members": [
              "DELAYED",
              "ARBITRAGE",
              "COMPLETED"
            ],
            "numberOfBytes": "1"
          },
          "t_int128": {
            "label": "int128",
            "numberOfBytes": "16"
          },
          "t_mapping(t_address,t_bool)": {
            "label": "mapping(address => bool)",
            "numberOfBytes": "32"
          },
          "t_mapping(t_address,t_struct(Bytes32Deque)8524_storage)": {
            "label": "mapping(address => struct DoubleEndedQueueUpgradeable.Bytes32Deque)",
            "numberOfBytes": "32"
          },
          "t_mapping(t_address,t_uint256)": {
            "label": "mapping(address => uint256)",
            "numberOfBytes": "32"
          },
          "t_mapping(t_bytes32,t_address)": {
            "label": "mapping(bytes32 => address)",
            "numberOfBytes": "32"
          },
          "t_mapping(t_bytes32,t_bool)": {
            "label": "mapping(bytes32 => bool)",
            "numberOfBytes": "32"
          },
          "t_mapping(t_bytes32,t_mapping(t_address,t_bool))": {
            "label": "mapping(bytes32 => mapping(address => bool))",
            "numberOfBytes": "32"
          },
          "t_mapping(t_bytes32,t_mapping(t_address,t_uint256))": {
            "label": "mapping(bytes32 => mapping(address => uint256))",
            "numberOfBytes": "32"
          },
          "t_mapping(t_bytes32,t_struct(AddressSet)9172_storage)": {
            "label": "mapping(bytes32 => struct EnumerableSetUpgradeable.AddressSet)",
            "numberOfBytes": "32"
          },
          "t_mapping(t_bytes32,t_struct(DelayConfig)16887_storage)": {
            "label": "mapping(bytes32 => struct DepositBoxERC20.DelayConfig)",
            "numberOfBytes": "32"
          },
          "t_mapping(t_bytes32,t_struct(RoleData)169_storage)": {
            "label": "mapping(bytes32 => struct AccessControlUpgradeable.RoleData)",
            "numberOfBytes": "32"
          },
          "t_mapping(t_bytes32,t_uint256)": {
            "label": "mapping(bytes32 => uint256)",
            "numberOfBytes": "32"
          },
          "t_mapping(t_int128,t_bytes32)": {
            "label": "mapping(int128 => bytes32)",
            "numberOfBytes": "32"
          },
          "t_mapping(t_uint256,t_struct(DelayedTransfer)16875_storage)": {
            "label": "mapping(uint256 => struct DepositBoxERC20.DelayedTransfer)",
            "numberOfBytes": "32"
          },
          "t_struct(AddressSet)9172_storage": {
            "label": "struct EnumerableSetUpgradeable.AddressSet",
            "members": [
              {
                "label": "_inner",
                "type": "t_struct(Set)8857_storage",
                "offset": 0,
                "slot": "0"
              }
            ],
            "numberOfBytes": "64"
          },
          "t_struct(Bytes32Deque)8524_storage": {
            "label": "struct DoubleEndedQueueUpgradeable.Bytes32Deque",
            "members": [
              {
                "label": "_begin",
                "type": "t_int128",
                "offset": 0,
                "slot": "0"
              },
              {
                "label": "_end",
                "type": "t_int128",
                "offset": 16,
                "slot": "0"
              },
              {
                "label": "_data",
                "type": "t_mapping(t_int128,t_bytes32)",
                "offset": 0,
                "slot": "1"
              }
            ],
            "numberOfBytes": "64"
          },
          "t_struct(DelayConfig)16887_storage": {
            "label": "struct DepositBoxERC20.DelayConfig",
            "members": [
              {
                "label": "bigTransferThreshold",
                "type": "t_mapping(t_address,t_uint256)",
                "offset": 0,
                "slot": "0"
              },
              {
                "label": "trustedReceivers",
                "type": "t_struct(AddressSet)9172_storage",
                "offset": 0,
                "slot": "1"
              },
              {
                "label": "transferDelay",
                "type": "t_uint256",
                "offset": 0,
                "slot": "3"
              },
              {
                "label": "arbitrageDuration",
                "type": "t_uint256",
                "offset": 0,
                "slot": "4"
              }
            ],
            "numberOfBytes": "160"
          },
          "t_struct(DelayedTransfer)16875_storage": {
            "label": "struct DepositBoxERC20.DelayedTransfer",
            "members": [
              {
                "label": "receiver",
                "type": "t_address",
                "offset": 0,
                "slot": "0"
              },
              {
                "label": "schainHash",
                "type": "t_bytes32",
                "offset": 0,
                "slot": "1"
              },
              {
                "label": "token",
                "type": "t_address",
                "offset": 0,
                "slot": "2"
              },
              {
                "label": "amount",
                "type": "t_uint256",
                "offset": 0,
                "slot": "3"
              },
              {
                "label": "untilTimestamp",
                "type": "t_uint256",
                "offset": 0,
                "slot": "4"
              },
              {
                "label": "status",
                "type": "t_enum(DelayedTransferStatus)16861",
                "offset": 0,
                "slot": "5"
              }
            ],
            "numberOfBytes": "192"
          },
          "t_struct(RoleData)169_storage": {
            "label": "struct AccessControlUpgradeable.RoleData",
            "members": [
              {
                "label": "members",
                "type": "t_mapping(t_address,t_bool)",
                "offset": 0,
                "slot": "0"
              },
              {
                "label": "adminRole",
                "type": "t_bytes32",
                "offset": 0,
                "slot": "1"
              }
            ],
            "numberOfBytes": "64"
          },
          "t_struct(Set)8857_storage": {
            "label": "struct EnumerableSetUpgradeable.Set",
            "members": [
              {
                "label": "_values",
                "type": "t_array(t_bytes32)dyn_storage",
                "offset": 0,
                "slot": "0"
              },
              {
                "label": "_indexes",
                "type": "t_mapping(t_bytes32,t_uint256)",
                "offset": 0,
                "slot": "1"
              }
            ],
            "numberOfBytes": "64"
          },
          "t_uint256": {
            "label": "uint256",
            "numberOfBytes": "32"
          },
          "t_uint8": {
            "label": "uint8",
            "numberOfBytes": "1"
          }
        },
        "namespaces": {}
      }
    },
    "94b00c814347019e4d919b37beebe418ccf3bbc4a28565ec701a6e68da51b042": {
      "address": "0xBDB8213143750aFf09cE06BAfB77692ea40898c9",
      "txHash": "0xd4ec29e857cb53029556560c518a49122aa4382fd54501f51195f77d66a09784",
      "layout": {
        "solcVersion": "0.8.16",
        "storage": [
          {
            "label": "_initialized",
            "offset": 0,
            "slot": "0",
            "type": "t_uint8",
            "contract": "Initializable",
            "src": "@openzeppelin/contracts-upgradeable/proxy/utils/Initializable.sol:63",
            "retypedFrom": "bool"
          },
          {
            "label": "_initializing",
            "offset": 1,
            "slot": "0",
            "type": "t_bool",
            "contract": "Initializable",
            "src": "@openzeppelin/contracts-upgradeable/proxy/utils/Initializable.sol:68"
          },
          {
            "label": "__gap",
            "offset": 0,
            "slot": "1",
            "type": "t_array(t_uint256)50_storage",
            "contract": "ContextUpgradeable",
            "src": "@openzeppelin/contracts-upgradeable/utils/ContextUpgradeable.sol:40"
          },
          {
            "label": "__gap",
            "offset": 0,
            "slot": "51",
            "type": "t_array(t_uint256)50_storage",
            "contract": "ERC165Upgradeable",
            "src": "@openzeppelin/contracts-upgradeable/utils/introspection/ERC165Upgradeable.sol:41"
          },
          {
            "label": "_roles",
            "offset": 0,
            "slot": "101",
            "type": "t_mapping(t_bytes32,t_struct(RoleData)169_storage)",
            "contract": "AccessControlUpgradeable",
            "src": "@openzeppelin/contracts-upgradeable/access/AccessControlUpgradeable.sol:57"
          },
          {
            "label": "__gap",
            "offset": 0,
            "slot": "102",
            "type": "t_array(t_uint256)49_storage",
            "contract": "AccessControlUpgradeable",
            "src": "@openzeppelin/contracts-upgradeable/access/AccessControlUpgradeable.sol:260"
          },
          {
            "label": "_roleMembers",
            "offset": 0,
            "slot": "151",
            "type": "t_mapping(t_bytes32,t_struct(AddressSet)9172_storage)",
            "contract": "AccessControlEnumerableUpgradeable",
            "src": "@openzeppelin/contracts-upgradeable/access/AccessControlEnumerableUpgradeable.sol:17"
          },
          {
            "label": "__gap",
            "offset": 0,
            "slot": "152",
            "type": "t_array(t_uint256)49_storage",
            "contract": "AccessControlEnumerableUpgradeable",
            "src": "@openzeppelin/contracts-upgradeable/access/AccessControlEnumerableUpgradeable.sol:76"
          },
          {
            "label": "contractManagerOfSkaleManager",
            "offset": 0,
            "slot": "201",
            "type": "t_contract(IContractManager)11020",
            "contract": "SkaleManagerClient",
            "src": "contracts/mainnet/SkaleManagerClient.sol:37"
          },
          {
            "label": "messageProxy",
            "offset": 0,
            "slot": "202",
            "type": "t_contract(IMessageProxyForMainnet)10412",
            "contract": "Twin",
            "src": "contracts/mainnet/Twin.sol:38"
          },
          {
            "label": "schainLinks",
            "offset": 0,
            "slot": "203",
            "type": "t_mapping(t_bytes32,t_address)",
            "contract": "Twin",
            "src": "contracts/mainnet/Twin.sol:39"
          },
          {
            "label": "linker",
            "offset": 0,
            "slot": "204",
            "type": "t_contract(ILinker)10325",
            "contract": "DepositBox",
            "src": "contracts/mainnet/DepositBox.sol:36"
          },
          {
            "label": "_automaticDeploy",
            "offset": 0,
            "slot": "205",
            "type": "t_mapping(t_bytes32,t_bool)",
            "contract": "DepositBox",
            "src": "contracts/mainnet/DepositBox.sol:39"
          },
          {
            "label": "_deprecatedSchainToERC721",
            "offset": 0,
            "slot": "206",
            "type": "t_mapping(t_bytes32,t_mapping(t_address,t_bool))",
            "contract": "DepositBoxERC721",
            "src": "contracts/mainnet/DepositBoxes/DepositBoxERC721.sol:46"
          },
          {
            "label": "transferredAmount",
            "offset": 0,
            "slot": "207",
            "type": "t_mapping(t_address,t_mapping(t_uint256,t_bytes32))",
            "contract": "DepositBoxERC721",
            "src": "contracts/mainnet/DepositBoxes/DepositBoxERC721.sol:47"
          },
          {
            "label": "_schainToERC721",
            "offset": 0,
            "slot": "208",
            "type": "t_mapping(t_bytes32,t_struct(AddressSet)9172_storage)",
            "contract": "DepositBoxERC721",
            "src": "contracts/mainnet/DepositBoxes/DepositBoxERC721.sol:48"
          }
        ],
        "types": {
          "t_address": {
            "label": "address",
            "numberOfBytes": "20"
          },
          "t_array(t_bytes32)dyn_storage": {
            "label": "bytes32[]",
            "numberOfBytes": "32"
          },
          "t_array(t_uint256)49_storage": {
            "label": "uint256[49]",
            "numberOfBytes": "1568"
          },
          "t_array(t_uint256)50_storage": {
            "label": "uint256[50]",
            "numberOfBytes": "1600"
          },
          "t_bool": {
            "label": "bool",
            "numberOfBytes": "1"
          },
          "t_bytes32": {
            "label": "bytes32",
            "numberOfBytes": "32"
          },
          "t_contract(IContractManager)11020": {
            "label": "contract IContractManager",
            "numberOfBytes": "20"
          },
          "t_contract(ILinker)10325": {
            "label": "contract ILinker",
            "numberOfBytes": "20"
          },
          "t_contract(IMessageProxyForMainnet)10412": {
            "label": "contract IMessageProxyForMainnet",
            "numberOfBytes": "20"
          },
          "t_mapping(t_address,t_bool)": {
            "label": "mapping(address => bool)",
            "numberOfBytes": "32"
          },
          "t_mapping(t_address,t_mapping(t_uint256,t_bytes32))": {
            "label": "mapping(address => mapping(uint256 => bytes32))",
            "numberOfBytes": "32"
          },
          "t_mapping(t_bytes32,t_address)": {
            "label": "mapping(bytes32 => address)",
            "numberOfBytes": "32"
          },
          "t_mapping(t_bytes32,t_bool)": {
            "label": "mapping(bytes32 => bool)",
            "numberOfBytes": "32"
          },
          "t_mapping(t_bytes32,t_mapping(t_address,t_bool))": {
            "label": "mapping(bytes32 => mapping(address => bool))",
            "numberOfBytes": "32"
          },
          "t_mapping(t_bytes32,t_struct(AddressSet)9172_storage)": {
            "label": "mapping(bytes32 => struct EnumerableSetUpgradeable.AddressSet)",
            "numberOfBytes": "32"
          },
          "t_mapping(t_bytes32,t_struct(RoleData)169_storage)": {
            "label": "mapping(bytes32 => struct AccessControlUpgradeable.RoleData)",
            "numberOfBytes": "32"
          },
          "t_mapping(t_bytes32,t_uint256)": {
            "label": "mapping(bytes32 => uint256)",
            "numberOfBytes": "32"
          },
          "t_mapping(t_uint256,t_bytes32)": {
            "label": "mapping(uint256 => bytes32)",
            "numberOfBytes": "32"
          },
          "t_struct(AddressSet)9172_storage": {
            "label": "struct EnumerableSetUpgradeable.AddressSet",
            "members": [
              {
                "label": "_inner",
                "type": "t_struct(Set)8857_storage",
                "offset": 0,
                "slot": "0"
              }
            ],
            "numberOfBytes": "64"
          },
          "t_struct(RoleData)169_storage": {
            "label": "struct AccessControlUpgradeable.RoleData",
            "members": [
              {
                "label": "members",
                "type": "t_mapping(t_address,t_bool)",
                "offset": 0,
                "slot": "0"
              },
              {
                "label": "adminRole",
                "type": "t_bytes32",
                "offset": 0,
                "slot": "1"
              }
            ],
            "numberOfBytes": "64"
          },
          "t_struct(Set)8857_storage": {
            "label": "struct EnumerableSetUpgradeable.Set",
            "members": [
              {
                "label": "_values",
                "type": "t_array(t_bytes32)dyn_storage",
                "offset": 0,
                "slot": "0"
              },
              {
                "label": "_indexes",
                "type": "t_mapping(t_bytes32,t_uint256)",
                "offset": 0,
                "slot": "1"
              }
            ],
            "numberOfBytes": "64"
          },
          "t_uint256": {
            "label": "uint256",
            "numberOfBytes": "32"
          },
          "t_uint8": {
            "label": "uint8",
            "numberOfBytes": "1"
          }
        },
        "namespaces": {}
      }
    },
    "afc327f085488a7d20ceed4e072edad2f2e6b29b4f867788fdb568baf85287fa": {
      "address": "0x16f294eE28142Dcd757133973A2689134B00f025",
      "txHash": "0x5a639fe85b57b1bd5bba8460572ab4abdd0933be7c6abfe0fa48803a23f4a228",
      "layout": {
        "solcVersion": "0.8.16",
        "storage": [
          {
            "label": "_initialized",
            "offset": 0,
            "slot": "0",
            "type": "t_uint8",
            "contract": "Initializable",
            "src": "@openzeppelin/contracts-upgradeable/proxy/utils/Initializable.sol:63",
            "retypedFrom": "bool"
          },
          {
            "label": "_initializing",
            "offset": 1,
            "slot": "0",
            "type": "t_bool",
            "contract": "Initializable",
            "src": "@openzeppelin/contracts-upgradeable/proxy/utils/Initializable.sol:68"
          },
          {
            "label": "__gap",
            "offset": 0,
            "slot": "1",
            "type": "t_array(t_uint256)50_storage",
            "contract": "ContextUpgradeable",
            "src": "@openzeppelin/contracts-upgradeable/utils/ContextUpgradeable.sol:40"
          },
          {
            "label": "__gap",
            "offset": 0,
            "slot": "51",
            "type": "t_array(t_uint256)50_storage",
            "contract": "ERC165Upgradeable",
            "src": "@openzeppelin/contracts-upgradeable/utils/introspection/ERC165Upgradeable.sol:41"
          },
          {
            "label": "_roles",
            "offset": 0,
            "slot": "101",
            "type": "t_mapping(t_bytes32,t_struct(RoleData)169_storage)",
            "contract": "AccessControlUpgradeable",
            "src": "@openzeppelin/contracts-upgradeable/access/AccessControlUpgradeable.sol:57"
          },
          {
            "label": "__gap",
            "offset": 0,
            "slot": "102",
            "type": "t_array(t_uint256)49_storage",
            "contract": "AccessControlUpgradeable",
            "src": "@openzeppelin/contracts-upgradeable/access/AccessControlUpgradeable.sol:260"
          },
          {
            "label": "_roleMembers",
            "offset": 0,
            "slot": "151",
            "type": "t_mapping(t_bytes32,t_struct(AddressSet)9172_storage)",
            "contract": "AccessControlEnumerableUpgradeable",
            "src": "@openzeppelin/contracts-upgradeable/access/AccessControlEnumerableUpgradeable.sol:17"
          },
          {
            "label": "__gap",
            "offset": 0,
            "slot": "152",
            "type": "t_array(t_uint256)49_storage",
            "contract": "AccessControlEnumerableUpgradeable",
            "src": "@openzeppelin/contracts-upgradeable/access/AccessControlEnumerableUpgradeable.sol:76"
          },
          {
            "label": "contractManagerOfSkaleManager",
            "offset": 0,
            "slot": "201",
            "type": "t_contract(IContractManager)11020",
            "contract": "SkaleManagerClient",
            "src": "contracts/mainnet/SkaleManagerClient.sol:37"
          },
          {
            "label": "messageProxy",
            "offset": 0,
            "slot": "202",
            "type": "t_contract(IMessageProxyForMainnet)10412",
            "contract": "Twin",
            "src": "contracts/mainnet/Twin.sol:38"
          },
          {
            "label": "schainLinks",
            "offset": 0,
            "slot": "203",
            "type": "t_mapping(t_bytes32,t_address)",
            "contract": "Twin",
            "src": "contracts/mainnet/Twin.sol:39"
          },
          {
            "label": "linker",
            "offset": 0,
            "slot": "204",
            "type": "t_contract(ILinker)10325",
            "contract": "DepositBox",
            "src": "contracts/mainnet/DepositBox.sol:36"
          },
          {
            "label": "_automaticDeploy",
            "offset": 0,
            "slot": "205",
            "type": "t_mapping(t_bytes32,t_bool)",
            "contract": "DepositBox",
            "src": "contracts/mainnet/DepositBox.sol:39"
          },
          {
            "label": "__gap",
            "offset": 0,
            "slot": "206",
            "type": "t_array(t_uint256)50_storage",
            "contract": "ERC1155ReceiverUpgradeable",
            "src": "@openzeppelin/contracts-upgradeable/token/ERC1155/utils/ERC1155ReceiverUpgradeable.sol:31"
          },
          {
            "label": "_deprecatedSchainToERC1155",
            "offset": 0,
            "slot": "256",
            "type": "t_mapping(t_bytes32,t_mapping(t_address,t_bool))",
            "contract": "DepositBoxERC1155",
            "src": "contracts/mainnet/DepositBoxes/DepositBoxERC1155.sol:49"
          },
          {
            "label": "transferredAmount",
            "offset": 0,
            "slot": "257",
            "type": "t_mapping(t_bytes32,t_mapping(t_address,t_mapping(t_uint256,t_uint256)))",
            "contract": "DepositBoxERC1155",
            "src": "contracts/mainnet/DepositBoxes/DepositBoxERC1155.sol:50"
          },
          {
            "label": "_schainToERC1155",
            "offset": 0,
            "slot": "258",
            "type": "t_mapping(t_bytes32,t_struct(AddressSet)9172_storage)",
            "contract": "DepositBoxERC1155",
            "src": "contracts/mainnet/DepositBoxes/DepositBoxERC1155.sol:51"
          }
        ],
        "types": {
          "t_address": {
            "label": "address",
            "numberOfBytes": "20"
          },
          "t_array(t_bytes32)dyn_storage": {
            "label": "bytes32[]",
            "numberOfBytes": "32"
          },
          "t_array(t_uint256)49_storage": {
            "label": "uint256[49]",
            "numberOfBytes": "1568"
          },
          "t_array(t_uint256)50_storage": {
            "label": "uint256[50]",
            "numberOfBytes": "1600"
          },
          "t_bool": {
            "label": "bool",
            "numberOfBytes": "1"
          },
          "t_bytes32": {
            "label": "bytes32",
            "numberOfBytes": "32"
          },
          "t_contract(IContractManager)11020": {
            "label": "contract IContractManager",
            "numberOfBytes": "20"
          },
          "t_contract(ILinker)10325": {
            "label": "contract ILinker",
            "numberOfBytes": "20"
          },
          "t_contract(IMessageProxyForMainnet)10412": {
            "label": "contract IMessageProxyForMainnet",
            "numberOfBytes": "20"
          },
          "t_mapping(t_address,t_bool)": {
            "label": "mapping(address => bool)",
            "numberOfBytes": "32"
          },
          "t_mapping(t_address,t_mapping(t_uint256,t_uint256))": {
            "label": "mapping(address => mapping(uint256 => uint256))",
            "numberOfBytes": "32"
          },
          "t_mapping(t_bytes32,t_address)": {
            "label": "mapping(bytes32 => address)",
            "numberOfBytes": "32"
          },
          "t_mapping(t_bytes32,t_bool)": {
            "label": "mapping(bytes32 => bool)",
            "numberOfBytes": "32"
          },
          "t_mapping(t_bytes32,t_mapping(t_address,t_bool))": {
            "label": "mapping(bytes32 => mapping(address => bool))",
            "numberOfBytes": "32"
          },
          "t_mapping(t_bytes32,t_mapping(t_address,t_mapping(t_uint256,t_uint256)))": {
            "label": "mapping(bytes32 => mapping(address => mapping(uint256 => uint256)))",
            "numberOfBytes": "32"
          },
          "t_mapping(t_bytes32,t_struct(AddressSet)9172_storage)": {
            "label": "mapping(bytes32 => struct EnumerableSetUpgradeable.AddressSet)",
            "numberOfBytes": "32"
          },
          "t_mapping(t_bytes32,t_struct(RoleData)169_storage)": {
            "label": "mapping(bytes32 => struct AccessControlUpgradeable.RoleData)",
            "numberOfBytes": "32"
          },
          "t_mapping(t_bytes32,t_uint256)": {
            "label": "mapping(bytes32 => uint256)",
            "numberOfBytes": "32"
          },
          "t_mapping(t_uint256,t_uint256)": {
            "label": "mapping(uint256 => uint256)",
            "numberOfBytes": "32"
          },
          "t_struct(AddressSet)9172_storage": {
            "label": "struct EnumerableSetUpgradeable.AddressSet",
            "members": [
              {
                "label": "_inner",
                "type": "t_struct(Set)8857_storage",
                "offset": 0,
                "slot": "0"
              }
            ],
            "numberOfBytes": "64"
          },
          "t_struct(RoleData)169_storage": {
            "label": "struct AccessControlUpgradeable.RoleData",
            "members": [
              {
                "label": "members",
                "type": "t_mapping(t_address,t_bool)",
                "offset": 0,
                "slot": "0"
              },
              {
                "label": "adminRole",
                "type": "t_bytes32",
                "offset": 0,
                "slot": "1"
              }
            ],
            "numberOfBytes": "64"
          },
          "t_struct(Set)8857_storage": {
            "label": "struct EnumerableSetUpgradeable.Set",
            "members": [
              {
                "label": "_values",
                "type": "t_array(t_bytes32)dyn_storage",
                "offset": 0,
                "slot": "0"
              },
              {
                "label": "_indexes",
                "type": "t_mapping(t_bytes32,t_uint256)",
                "offset": 0,
                "slot": "1"
              }
            ],
            "numberOfBytes": "64"
          },
          "t_uint256": {
            "label": "uint256",
            "numberOfBytes": "32"
          },
          "t_uint8": {
            "label": "uint8",
            "numberOfBytes": "1"
          }
        },
        "namespaces": {}
      }
    },
    "a0fd8cd602a55abac0cf4c93794fef1e50b6df9f70fea43e5f01bca3efa61989": {
      "address": "0x8dAD190615c2c00584cA65bc7DEf27B7CF335752",
      "txHash": "0x3864e6c3fc4692a1446ad24c7b8149a4338519baf8754768ca485becbe10c18a",
      "layout": {
        "solcVersion": "0.8.16",
        "storage": [
          {
            "label": "_initialized",
            "offset": 0,
            "slot": "0",
            "type": "t_uint8",
            "contract": "Initializable",
            "src": "@openzeppelin/contracts-upgradeable/proxy/utils/Initializable.sol:63",
            "retypedFrom": "bool"
          },
          {
            "label": "_initializing",
            "offset": 1,
            "slot": "0",
            "type": "t_bool",
            "contract": "Initializable",
            "src": "@openzeppelin/contracts-upgradeable/proxy/utils/Initializable.sol:68"
          },
          {
            "label": "__gap",
            "offset": 0,
            "slot": "1",
            "type": "t_array(t_uint256)50_storage",
            "contract": "ContextUpgradeable",
            "src": "@openzeppelin/contracts-upgradeable/utils/ContextUpgradeable.sol:40"
          },
          {
            "label": "__gap",
            "offset": 0,
            "slot": "51",
            "type": "t_array(t_uint256)50_storage",
            "contract": "ERC165Upgradeable",
            "src": "@openzeppelin/contracts-upgradeable/utils/introspection/ERC165Upgradeable.sol:41"
          },
          {
            "label": "_roles",
            "offset": 0,
            "slot": "101",
            "type": "t_mapping(t_bytes32,t_struct(RoleData)169_storage)",
            "contract": "AccessControlUpgradeable",
            "src": "@openzeppelin/contracts-upgradeable/access/AccessControlUpgradeable.sol:57"
          },
          {
            "label": "__gap",
            "offset": 0,
            "slot": "102",
            "type": "t_array(t_uint256)49_storage",
            "contract": "AccessControlUpgradeable",
            "src": "@openzeppelin/contracts-upgradeable/access/AccessControlUpgradeable.sol:260"
          },
          {
            "label": "_roleMembers",
            "offset": 0,
            "slot": "151",
            "type": "t_mapping(t_bytes32,t_struct(AddressSet)9172_storage)",
            "contract": "AccessControlEnumerableUpgradeable",
            "src": "@openzeppelin/contracts-upgradeable/access/AccessControlEnumerableUpgradeable.sol:17"
          },
          {
            "label": "__gap",
            "offset": 0,
            "slot": "152",
            "type": "t_array(t_uint256)49_storage",
            "contract": "AccessControlEnumerableUpgradeable",
            "src": "@openzeppelin/contracts-upgradeable/access/AccessControlEnumerableUpgradeable.sol:76"
          },
          {
            "label": "contractManagerOfSkaleManager",
            "offset": 0,
            "slot": "201",
            "type": "t_contract(IContractManager)11020",
            "contract": "SkaleManagerClient",
            "src": "contracts/mainnet/SkaleManagerClient.sol:37"
          },
          {
            "label": "messageProxy",
            "offset": 0,
            "slot": "202",
            "type": "t_contract(IMessageProxyForMainnet)10412",
            "contract": "Twin",
            "src": "contracts/mainnet/Twin.sol:38"
          },
          {
            "label": "schainLinks",
            "offset": 0,
            "slot": "203",
            "type": "t_mapping(t_bytes32,t_address)",
            "contract": "Twin",
            "src": "contracts/mainnet/Twin.sol:39"
          },
          {
            "label": "linker",
            "offset": 0,
            "slot": "204",
            "type": "t_contract(ILinker)10325",
            "contract": "DepositBox",
            "src": "contracts/mainnet/DepositBox.sol:36"
          },
          {
            "label": "_automaticDeploy",
            "offset": 0,
            "slot": "205",
            "type": "t_mapping(t_bytes32,t_bool)",
            "contract": "DepositBox",
            "src": "contracts/mainnet/DepositBox.sol:39"
          },
          {
            "label": "_deprecatedSchainToERC721",
            "offset": 0,
            "slot": "206",
            "type": "t_mapping(t_bytes32,t_mapping(t_address,t_bool))",
            "contract": "DepositBoxERC721",
            "src": "contracts/mainnet/DepositBoxes/DepositBoxERC721.sol:46"
          },
          {
            "label": "transferredAmount",
            "offset": 0,
            "slot": "207",
            "type": "t_mapping(t_address,t_mapping(t_uint256,t_bytes32))",
            "contract": "DepositBoxERC721",
            "src": "contracts/mainnet/DepositBoxes/DepositBoxERC721.sol:47"
          },
          {
            "label": "_schainToERC721",
            "offset": 0,
            "slot": "208",
            "type": "t_mapping(t_bytes32,t_struct(AddressSet)9172_storage)",
            "contract": "DepositBoxERC721",
            "src": "contracts/mainnet/DepositBoxes/DepositBoxERC721.sol:48"
          }
        ],
        "types": {
          "t_address": {
            "label": "address",
            "numberOfBytes": "20"
          },
          "t_array(t_bytes32)dyn_storage": {
            "label": "bytes32[]",
            "numberOfBytes": "32"
          },
          "t_array(t_uint256)49_storage": {
            "label": "uint256[49]",
            "numberOfBytes": "1568"
          },
          "t_array(t_uint256)50_storage": {
            "label": "uint256[50]",
            "numberOfBytes": "1600"
          },
          "t_bool": {
            "label": "bool",
            "numberOfBytes": "1"
          },
          "t_bytes32": {
            "label": "bytes32",
            "numberOfBytes": "32"
          },
          "t_contract(IContractManager)11020": {
            "label": "contract IContractManager",
            "numberOfBytes": "20"
          },
          "t_contract(ILinker)10325": {
            "label": "contract ILinker",
            "numberOfBytes": "20"
          },
          "t_contract(IMessageProxyForMainnet)10412": {
            "label": "contract IMessageProxyForMainnet",
            "numberOfBytes": "20"
          },
          "t_mapping(t_address,t_bool)": {
            "label": "mapping(address => bool)",
            "numberOfBytes": "32"
          },
          "t_mapping(t_address,t_mapping(t_uint256,t_bytes32))": {
            "label": "mapping(address => mapping(uint256 => bytes32))",
            "numberOfBytes": "32"
          },
          "t_mapping(t_bytes32,t_address)": {
            "label": "mapping(bytes32 => address)",
            "numberOfBytes": "32"
          },
          "t_mapping(t_bytes32,t_bool)": {
            "label": "mapping(bytes32 => bool)",
            "numberOfBytes": "32"
          },
          "t_mapping(t_bytes32,t_mapping(t_address,t_bool))": {
            "label": "mapping(bytes32 => mapping(address => bool))",
            "numberOfBytes": "32"
          },
          "t_mapping(t_bytes32,t_struct(AddressSet)9172_storage)": {
            "label": "mapping(bytes32 => struct EnumerableSetUpgradeable.AddressSet)",
            "numberOfBytes": "32"
          },
          "t_mapping(t_bytes32,t_struct(RoleData)169_storage)": {
            "label": "mapping(bytes32 => struct AccessControlUpgradeable.RoleData)",
            "numberOfBytes": "32"
          },
          "t_mapping(t_bytes32,t_uint256)": {
            "label": "mapping(bytes32 => uint256)",
            "numberOfBytes": "32"
          },
          "t_mapping(t_uint256,t_bytes32)": {
            "label": "mapping(uint256 => bytes32)",
            "numberOfBytes": "32"
          },
          "t_struct(AddressSet)9172_storage": {
            "label": "struct EnumerableSetUpgradeable.AddressSet",
            "members": [
              {
                "label": "_inner",
                "type": "t_struct(Set)8857_storage",
                "offset": 0,
                "slot": "0"
              }
            ],
            "numberOfBytes": "64"
          },
          "t_struct(RoleData)169_storage": {
            "label": "struct AccessControlUpgradeable.RoleData",
            "members": [
              {
                "label": "members",
                "type": "t_mapping(t_address,t_bool)",
                "offset": 0,
                "slot": "0"
              },
              {
                "label": "adminRole",
                "type": "t_bytes32",
                "offset": 0,
                "slot": "1"
              }
            ],
            "numberOfBytes": "64"
          },
          "t_struct(Set)8857_storage": {
            "label": "struct EnumerableSetUpgradeable.Set",
            "members": [
              {
                "label": "_values",
                "type": "t_array(t_bytes32)dyn_storage",
                "offset": 0,
                "slot": "0"
              },
              {
                "label": "_indexes",
                "type": "t_mapping(t_bytes32,t_uint256)",
                "offset": 0,
                "slot": "1"
              }
            ],
            "numberOfBytes": "64"
          },
          "t_uint256": {
            "label": "uint256",
            "numberOfBytes": "32"
          },
          "t_uint8": {
            "label": "uint8",
            "numberOfBytes": "1"
          }
        },
        "namespaces": {}
      }
    }
  }
}
